liru/__init__.py
liru/__init__.pyi
liru/__version__.py
liru/_liru_core.cp314-win_amd64.pyd
liru/py.typed
liru/receiver.py
liru/sender.py
liru/Spout.dll
liru-0.2.6.dist-info/METADATA
liru-0.2.6.dist-info/WHEEL
liru-0.2.6.dist-info/licenses/LICENSE
liru-0.2.6.dist-info/licenses/THIRD_PARTY_LICENSES.txt
liru-0.2.6.dist-info/RECORD
