Metadata-Version: 2.2
Name: liru
Version: 0.2.6
Summary: High-performance Python wrapper for Spout 2.007 GPU texture sharing
Keywords: spout,gpu,texture-sharing,realtime,video,opengl,moderngl
Author-Email: =?utf-8?q?Lauri_M=C3=A4ki?= <laurimaeki@gmail.com>
Maintainer-Email: =?utf-8?q?Lauri_M=C3=A4ki?= <laurimaeki@gmail.com>
License: BSD-2-Clause
Classifier: Development Status :: 3 - Alpha
Classifier: Intended Audience :: Developers
Classifier: License :: OSI Approved :: BSD License
Classifier: Operating System :: Microsoft :: Windows
Classifier: Programming Language :: Python :: 3
Classifier: Programming Language :: Python :: 3.13
Classifier: Programming Language :: Python :: 3.14
Classifier: Programming Language :: Python :: 3.15
Classifier: Programming Language :: C++
Classifier: Topic :: Multimedia :: Video
Classifier: Topic :: Software Development :: Libraries :: Python Modules
Project-URL: Homepage, https://github.com/Ranttali/liru
Project-URL: Documentation, https://github.com/Ranttali/liru/tree/main/docs
Project-URL: Repository, https://github.com/Ranttali/liru
Project-URL: Issues, https://github.com/Ranttali/liru/issues
Project-URL: Changelog, https://github.com/Ranttali/liru/blob/main/CHANGELOG.md
Requires-Python: >=3.13
Provides-Extra: dev
Requires-Dist: pytest>=8.3.0; extra == "dev"
Requires-Dist: pytest-benchmark>=4.0.0; extra == "dev"
Requires-Dist: pytest-timeout>=2.2.0; extra == "dev"
Requires-Dist: black>=24.0.0; extra == "dev"
Requires-Dist: ruff>=0.6.0; extra == "dev"
Requires-Dist: mypy>=1.11.0; extra == "dev"
Requires-Dist: moderngl>=5.11.0; extra == "dev"
Requires-Dist: numpy>=2.0.0; extra == "dev"
Requires-Dist: build>=1.2.0; extra == "dev"
Requires-Dist: twine>=5.1.0; extra == "dev"
